[
    {
        "id": "7xK9",
        "category": "Fiction"
    },
    {
        "id": "L3mR",
        "category": "Non-Fiction"
    },
    {
        "id": "P8q2",
        "category": "Science Fiction"
    },
    {
        "id": "Z5fT",
        "category": "Mystery"
    },
    {
        "id": "A1nJ",
        "category": "Biography"
    },
    {
        "id": "H6wY",
        "category": "History"
    },
    {
        "id": "U4cB",
        "category": "Self-Help"
    },
    {
        "id": "G9sX",
        "category": "Children's"
    },
    {
        "id": "D2vM",
        "category": "Romance"
    },
    {
        "id": "E7kF",
        "category": "Thriller"
    }
]
